django_turnit/fields.py
django_turnit/utilities.py
django_turnit/models.py
django_turnit/__init__.py
django_turnit/tests.py
django_turnit/thumbnailer.py
django_turnit/conf.py
django_turnit/backends/gs.py
django_turnit/backends/base.py
django_turnit/backends/poppler.py
django_turnit/backends/pdftocairo.py
django_turnit/backends/__init__.py
django_turnit/backends/pdftoppm.py
django_turnit/management/__init__.py
django_turnit/management/commands/__init__.py
django_turnit/management/commands/turnit.py
django_turnit/templatetags/__init__.py
django_turnit/templatetags/turnit_tags.py
django_turnit/fabfile/__init__.py
django_turnit/fabfile/conf.py
django_turnit/migrations/0003_auto_20160315_1040.py
django_turnit/migrations/0004_auto_20160315_1051.py
django_turnit/migrations/0001_initial.py
django_turnit/migrations/0002_pdffilepage_file_size.py
django_turnit/migrations/__init__.py
django_turnit/migrations/0005_pdffilepage_pdffile_hash.py
django_turnit-0.1.3a1.dist-info/RECORD
django_turnit-0.1.3a1.dist-info/DESCRIPTION.rst
django_turnit-0.1.3a1.dist-info/METADATA
django_turnit-0.1.3a1.dist-info/WHEEL
django_turnit-0.1.3a1.dist-info/top_level.txt
django_turnit-0.1.3a1.dist-info/metadata.json
