Metadata-Version: 2.0
Name: django-turnit
Version: 0.1.3a1
Summary: PDF thumbnailer and viewer for django applications
Home-page: https://gitlab.com/frague59/django-turnit
Author: François GUÉRIN
Author-email: frague59@gmail.com
License: Modified BSD
Download-URL: https://gitlab.com/frague59/django-turnit/repository/archive.zip?ref=master
Keywords: django,PDF,turn.js
Platform: UNKNOWN
Classifier: Development Status :: 3 - Alpha
Classifier: Intended Audience :: Developers
Classifier: Framework :: Django :: 1.8
Classifier: Programming Language :: Python :: 2.7
Classifier: License :: OSI Approved :: BSD License
Requires-Dist: docutils (>=0.3)
Requires-Dist: django (>=1.8,<1.9)
Requires-Dist: django-appconf (>=1.0)
Requires-Dist: pdfminer
